coverall/__init__.py
coverall/cover.py
coverall-1.0.5.dist-info/LICENSE.txt
coverall-1.0.5.dist-info/METADATA
coverall-1.0.5.dist-info/WHEEL
coverall-1.0.5.dist-info/top_level.txt
coverall-1.0.5.dist-info/RECORD
