Metadata-Version: 2.1
Name: coverall
Version: 1.0.5
Summary: Useful tools to work through Exact Cover, Set Cover, and Max Cover Problems
Download-URL: https://pypi.org/project/coverall/
Author: Brancen Clement
Author-email: Brancenc@gmail.com
License: MIT
Keywords: MaxCover,SetCover,ExactCover
License-File: LICENSE.txt
Requires-Dist: bitarray
